mdm/__init__.py
mdm/__main__.py
mdm/mdm.py
mdm-0.9.2.dist-info/LICENSE
mdm-0.9.2.dist-info/METADATA
mdm-0.9.2.dist-info/WHEEL
mdm-0.9.2.dist-info/entry_points.txt
mdm-0.9.2.dist-info/top_level.txt
mdm-0.9.2.dist-info/RECORD
