Metadata-Version: 2.1
Name: mdm
Version: 0.9.2
Summary: A middleware data manager for at least MOOS-IvP and ROS
Home-page: https://github.com/raymondturrisi/mdm
Author: Raymond Turrisi
Author-email: <rturrisi@mit.edu>
License: MIT
Keywords: python,moos,moos-ivp,ros,ros2,data management,data extraction,csv,json
Classifier: Development Status :: 1 - Planning
Classifier: Intended Audience :: Developers
Classifier: Programming Language :: Python :: 3
Classifier: Operating System :: Unix
Classifier: Operating System :: MacOS :: MacOS X
Classifier: Operating System :: Microsoft :: Windows
License-File: LICENSE
